{
  "id": "cgpi-steel",
  "category": "material",
  "name": "鉄鋼関連 企業物価指数",
  "description": "鉄鋼関連価格の公的な推移を示す指標。鋼材を使用する加工分野の価格協議資料として、市場全体の上昇傾向の背景説明に用いる。",
  "publisher": "日本銀行",
  "sourceName": "企業物価指数（2020年基準）",
  "sourceUrl": "https://www.boj.or.jp/statistics/pi/cgpi_release/",
  "sourceDocumentUrl": "https://www.boj.or.jp/statistics/outline/exp/pi/cgpi_2020/",
  "seriesName": "国内企業物価指数 / 鉄鋼",
  "unit": "指数（2020年平均=100）",
  "baseYear": "2020",
  "frequency": "monthly",
  "publishedAt": "2026-06-10",
  "retrievedAt": "2026-06-27",
  "quality": "official_manual",
  "calculationNote": "2020年平均=100。基準年比は最新値と100を比較。前年比は同月の前年値と比較。出典: 日本銀行 国内企業物価指数（系列コード PRCG20_2200920001、2026年5月速報）。",
  "negotiationUse": "鋼材価格そのものではなく、鉄鋼関連価格の公的な上昇傾向を示す背景資料として使用する。自社の仕入明細や材料商社からの改定通知と併せて提示する。",
  "values": [
    {
      "period": "2016-01",
      "value": 86.5
    },
    {
      "period": "2016-02",
      "value": 86.1
    },
    {
      "period": "2016-03",
      "value": 85.8
    },
    {
      "period": "2016-04",
      "value": 84.4
    },
    {
      "period": "2016-05",
      "value": 84.6
    },
    {
      "period": "2016-06",
      "value": 84.7
    },
    {
      "period": "2016-07",
      "value": 84.7
    },
    {
      "period": "2016-08",
      "value": 84.8
    },
    {
      "period": "2016-09",
      "value": 84.8
    },
    {
      "period": "2016-10",
      "value": 86.4
    },
    {
      "period": "2016-11",
      "value": 86.9
    },
    {
      "period": "2016-12",
      "value": 87.8
    },
    {
      "period": "2017-01",
      "value": 90.1
    },
    {
      "period": "2017-02",
      "value": 91
    },
    {
      "period": "2017-03",
      "value": 91.5
    },
    {
      "period": "2017-04",
      "value": 93.5
    },
    {
      "period": "2017-05",
      "value": 94.1
    },
    {
      "period": "2017-06",
      "value": 94.2
    },
    {
      "period": "2017-07",
      "value": 94.3
    },
    {
      "period": "2017-08",
      "value": 94.5
    },
    {
      "period": "2017-09",
      "value": 94.8
    },
    {
      "period": "2017-10",
      "value": 95
    },
    {
      "period": "2017-11",
      "value": 95.3
    },
    {
      "period": "2017-12",
      "value": 95.6
    },
    {
      "period": "2018-01",
      "value": 96.4
    },
    {
      "period": "2018-02",
      "value": 96.6
    },
    {
      "period": "2018-03",
      "value": 97.1
    },
    {
      "period": "2018-04",
      "value": 98.3
    },
    {
      "period": "2018-05",
      "value": 98.7
    },
    {
      "period": "2018-06",
      "value": 99
    },
    {
      "period": "2018-07",
      "value": 98.9
    },
    {
      "period": "2018-08",
      "value": 99.1
    },
    {
      "period": "2018-09",
      "value": 99.3
    },
    {
      "period": "2018-10",
      "value": 99.6
    },
    {
      "period": "2018-11",
      "value": 99.6
    },
    {
      "period": "2018-12",
      "value": 99.7
    },
    {
      "period": "2019-01",
      "value": 99.6
    },
    {
      "period": "2019-02",
      "value": 99.6
    },
    {
      "period": "2019-03",
      "value": 99.7
    },
    {
      "period": "2019-04",
      "value": 100.5
    },
    {
      "period": "2019-05",
      "value": 100.5
    },
    {
      "period": "2019-06",
      "value": 100.5
    },
    {
      "period": "2019-07",
      "value": 100.5
    },
    {
      "period": "2019-08",
      "value": 100.4
    },
    {
      "period": "2019-09",
      "value": 100.4
    },
    {
      "period": "2019-10",
      "value": 102.1
    },
    {
      "period": "2019-11",
      "value": 102.1
    },
    {
      "period": "2019-12",
      "value": 102.1
    },
    {
      "period": "2020-01",
      "value": 101.7
    },
    {
      "period": "2020-02",
      "value": 101.6
    },
    {
      "period": "2020-03",
      "value": 101.3
    },
    {
      "period": "2020-04",
      "value": 100.1
    },
    {
      "period": "2020-05",
      "value": 99.7
    },
    {
      "period": "2020-06",
      "value": 99.5
    },
    {
      "period": "2020-07",
      "value": 99.2
    },
    {
      "period": "2020-08",
      "value": 99.2
    },
    {
      "period": "2020-09",
      "value": 99.1
    },
    {
      "period": "2020-10",
      "value": 99.3
    },
    {
      "period": "2020-11",
      "value": 99.5
    },
    {
      "period": "2020-12",
      "value": 99.9
    },
    {
      "period": "2021-01",
      "value": 102
    },
    {
      "period": "2021-02",
      "value": 103.1
    },
    {
      "period": "2021-03",
      "value": 103.8
    },
    {
      "period": "2021-04",
      "value": 107.9
    },
    {
      "period": "2021-05",
      "value": 110.1
    },
    {
      "period": "2021-06",
      "value": 112.4
    },
    {
      "period": "2021-07",
      "value": 115.2
    },
    {
      "period": "2021-08",
      "value": 117.1
    },
    {
      "period": "2021-09",
      "value": 118.7
    },
    {
      "period": "2021-10",
      "value": 127.1
    },
    {
      "period": "2021-11",
      "value": 129.4
    },
    {
      "period": "2021-12",
      "value": 130.3
    },
    {
      "period": "2022-01",
      "value": 132.5
    },
    {
      "period": "2022-02",
      "value": 133.1
    },
    {
      "period": "2022-03",
      "value": 134.1
    },
    {
      "period": "2022-04",
      "value": 139.4
    },
    {
      "period": "2022-05",
      "value": 141.6
    },
    {
      "period": "2022-06",
      "value": 143.3
    },
    {
      "period": "2022-07",
      "value": 147.7
    },
    {
      "period": "2022-08",
      "value": 150
    },
    {
      "period": "2022-09",
      "value": 151
    },
    {
      "period": "2022-10",
      "value": 158.3
    },
    {
      "period": "2022-11",
      "value": 158.4
    },
    {
      "period": "2022-12",
      "value": 157.6
    },
    {
      "period": "2023-01",
      "value": 157.8
    },
    {
      "period": "2023-02",
      "value": 157.8
    },
    {
      "period": "2023-03",
      "value": 157.6
    },
    {
      "period": "2023-04",
      "value": 155
    },
    {
      "period": "2023-05",
      "value": 154.3
    },
    {
      "period": "2023-06",
      "value": 154.4
    },
    {
      "period": "2023-07",
      "value": 153.9
    },
    {
      "period": "2023-08",
      "value": 153.8
    },
    {
      "period": "2023-09",
      "value": 153.2
    },
    {
      "period": "2023-10",
      "value": 152.6
    },
    {
      "period": "2023-11",
      "value": 152.4
    },
    {
      "period": "2023-12",
      "value": 152.2
    },
    {
      "period": "2024-01",
      "value": 152.6
    },
    {
      "period": "2024-02",
      "value": 152.7
    },
    {
      "period": "2024-03",
      "value": 152.7
    },
    {
      "period": "2024-04",
      "value": 153.3
    },
    {
      "period": "2024-05",
      "value": 153.6
    },
    {
      "period": "2024-06",
      "value": 153.8
    },
    {
      "period": "2024-07",
      "value": 153.8
    },
    {
      "period": "2024-08",
      "value": 153.9
    },
    {
      "period": "2024-09",
      "value": 153.8
    },
    {
      "period": "2024-10",
      "value": 152.4
    },
    {
      "period": "2024-11",
      "value": 151.8
    },
    {
      "period": "2024-12",
      "value": 151.5
    },
    {
      "period": "2025-01",
      "value": 149.7
    },
    {
      "period": "2025-02",
      "value": 149.6
    },
    {
      "period": "2025-03",
      "value": 149
    },
    {
      "period": "2025-04",
      "value": 145
    },
    {
      "period": "2025-05",
      "value": 144.7
    },
    {
      "period": "2025-06",
      "value": 144.5
    },
    {
      "period": "2025-07",
      "value": 143.6
    },
    {
      "period": "2025-08",
      "value": 143.2
    },
    {
      "period": "2025-09",
      "value": 142.8
    },
    {
      "period": "2025-10",
      "value": 141.5
    },
    {
      "period": "2025-11",
      "value": 141.2
    },
    {
      "period": "2025-12",
      "value": 141.1
    },
    {
      "period": "2026-01",
      "value": 141.2
    },
    {
      "period": "2026-02",
      "value": 141.5
    },
    {
      "period": "2026-03",
      "value": 141.7
    },
    {
      "period": "2026-04",
      "value": 142.3
    },
    {
      "period": "2026-05",
      "value": 143
    }
  ]
}
